<?xml version="1.0" encoding="UTF-8"?>
<quiz>
<!-- question: 0  -->
  <question type="category">
    <category>
        <text>$course$/Linear Algebra/one_i/Gauss's method</text>

    </category>
  </question>

<!-- question: 3  -->
  <question type="multichoice">
    <name>
      <text>Appropriate row operation</text>
    </name>
    <questiontext format="html">
      <text><![CDATA[<p>For this linear system @d\begin{array}{rcrcrcr} 3x &amp;+ &amp;2y &amp;- &amp;z &amp;= &amp;4\\ x &amp;- &amp;y &amp;+&amp;z &amp;= &amp;0\\ 5x &amp; &amp; &amp;+&amp;z &amp;= &amp;-1/2\\ &amp; &amp;y &amp;- &amp;4z&amp;= &amp;9 \end{array}@d what is the row operation that will, in one step, use the first row to eliminate the @ix@i in the third row?</p>]]></text>
    </questiontext>
    <generalfeedback format="html">
      <text></text>
    </generalfeedback>
    <defaultgrade>1.0000000</defaultgrade>
    <penalty>0.3333333</penalty>
    <hidden>0</hidden>
    <single>true</single>
    <shuffleanswers>true</shuffleanswers>
    <answernumbering>abc</answernumbering>
    <correctfeedback format="html">
      <text></text>
    </correctfeedback>
    <partiallycorrectfeedback format="html">
      <text></text>
    </partiallycorrectfeedback>
    <incorrectfeedback format="html">
      <text></text>
    </incorrectfeedback>
    <answer fraction="0" format="html">
      <text><![CDATA[<p>@i(1/3)\rho_1+\rho_3@i</p>]]></text>
      <feedback format="html">
        <text><![CDATA[<p>You must eliminate the @i5x@i.</p>]]></text>
      </feedback>
    </answer>
    <answer fraction="100" format="html">
      <text><![CDATA[<p>@i(-5/3)\rho_1+\rho_3@i</p>]]></text>
      <feedback format="html">
        <text></text>
      </feedback>
    </answer>
    <answer fraction="0" format="html">
      <text><![CDATA[<p>@i(5/3)\rho_1+\rho_3@i</p>]]></text>
      <feedback format="html">
        <text><![CDATA[<p>Eliminate it, not add to it.</p>]]></text>
      </feedback>
    </answer>
    <answer fraction="0" format="html">
      <text><![CDATA[<p>@i-5\rho_1+\rho_3@i</p>]]></text>
      <feedback format="html">
        <text><![CDATA[<p>Scale the first row to offset the leading entry in the third row.</p>]]></text>
      </feedback>
    </answer>
    <answer fraction="0" format="html">
      <text><![CDATA[<p>@i(-1/3)\rho_1+\rho_2@i</p>]]></text>
      <feedback format="html">
        <text><![CDATA[<p>The question is to eliminate in the third row</p>]]></text>
      </feedback>
    </answer>
  </question>

<!-- question: 0  -->
  <question type="category">
    <category>
        <text>$course$/Linear Algebra/one_i/Describing the solution set</text>

    </category>
  </question>

<!-- question: 12  -->
  <question type="multichoice">
    <name>
      <text>Parametrize solution set four unknowns</text>
    </name>
    <questiontext format="html">
      <text><![CDATA[<p>Paramatrize the solution set of this system.</p>
<p>@d\begin{array}{rcrcrcrcr} x &amp;+ &amp;y &amp;+ &amp;w &amp;= &amp;1\\ 2x &amp;- &amp;y &amp;+ &amp;2z &amp;= &amp;0 \end{array}@d</p>
<p>Express the answer in vector notation.</p>]]></text>
    </questiontext>
    <generalfeedback format="html">
      <text></text>
    </generalfeedback>
    <defaultgrade>1.0000000</defaultgrade>
    <penalty>0.3333333</penalty>
    <hidden>0</hidden>
    <single>true</single>
    <shuffleanswers>true</shuffleanswers>
    <answernumbering>abc</answernumbering>
    <correctfeedback format="html">
      <text></text>
    </correctfeedback>
    <partiallycorrectfeedback format="html">
      <text></text>
    </partiallycorrectfeedback>
    <incorrectfeedback format="html">
      <text></text>
    </incorrectfeedback>
    <answer fraction="100" format="html">
      <text><![CDATA[<p>@i\{\begin{pmatrix} x\\ y\\ z\\ w\end{pmatrix} =\begin{pmatrix} 1/3\\ 2/3\\ 0\\ 0\end{pmatrix}+ \begin{pmatrix} -2/3\\ 2/3\\ 1\\ 0\end{pmatrix}z +\begin{pmatrix} -1/3\\ -2/3\\ 0\\ 1\end{pmatrix}w\}@i</p>]]></text>
      <feedback format="html">
        <text></text>
      </feedback>
    </answer>
    <answer fraction="0" format="html">
      <text><![CDATA[<p>@i\{\begin{pmatrix} x\\ y\\ z\\ w\end{pmatrix} =\begin{pmatrix} -1/3\\ 2/3\\ 0\\ 0\end{pmatrix}+ \begin{pmatrix} -2/3\\ 2/3\\ 1\\ 0\end{pmatrix}z +\begin{pmatrix} 1/3\\ -2/3\\ 0\\ 1\end{pmatrix}w\}@i</p>]]></text>
      <feedback format="html">
        <text></text>
      </feedback>
    </answer>
    <answer fraction="0" format="html">
      <text><![CDATA[<p>@i\{\begin{pmatrix} x\\ y\\ z\\ w\end{pmatrix} =\begin{pmatrix} 1/3\\ -2/3\\ 0\\ 0\end{pmatrix}+ \begin{pmatrix} 2/3\\ 2/3\\ -1\\ 0\end{pmatrix}z +\begin{pmatrix} -1/3\\ -2/3\\ 0\\ -1\end{pmatrix}w\}@i</p>]]></text>
      <feedback format="html">
        <text></text>
      </feedback>
    </answer>
    <answer fraction="0" format="html">
      <text><![CDATA[<p>@i\{\begin{pmatrix} x\\ y\\ z\\ w\end{pmatrix} =\begin{pmatrix} 1/3\\ 2/3\\ 0\\ 0\end{pmatrix}+ \begin{pmatrix} 2/3\\ -1/3\\ 1\\ 0\end{pmatrix}z +\begin{pmatrix} -1/3\\ -2/3\\ 0\\ 1\end{pmatrix}w\}@i</p>]]></text>
      <feedback format="html">
        <text></text>
      </feedback>
    </answer>
  </question>

<!-- question: 11  -->
  <question type="multichoice">
    <name>
      <text>Parametrize solution set three unknowns</text>
    </name>
    <questiontext format="html">
      <text><![CDATA[<p>Paramatrize the solution set of this linear system.</p>
<p>@d\begin{array}{rcrcrcr} x &amp;+ &amp;y &amp;+ &amp;2z &amp;= &amp;4\\ x &amp;+ &amp;2y &amp;- &amp;z &amp;= &amp;2 \end{array}@d</p>]]></text>
    </questiontext>
    <generalfeedback format="html">
      <text></text>
    </generalfeedback>
    <defaultgrade>1.0000000</defaultgrade>
    <penalty>0.3333333</penalty>
    <hidden>0</hidden>
    <single>true</single>
    <shuffleanswers>true</shuffleanswers>
    <answernumbering>abc</answernumbering>
    <correctfeedback format="html">
      <text></text>
    </correctfeedback>
    <partiallycorrectfeedback format="html">
      <text></text>
    </partiallycorrectfeedback>
    <incorrectfeedback format="html">
      <text></text>
    </incorrectfeedback>
    <answer fraction="100" format="html">
      <text><![CDATA[<p>@d\{(x,y,z) | x=-5z+6\text{ and } y=3z-2\}@d</p>]]></text>
      <feedback format="html">
        <text></text>
      </feedback>
    </answer>
    <answer fraction="0" format="html">
      <text><![CDATA[<p>@d\{(x,y,z)| x=-5z+6\text{ and } y=-3z-2\}@d</p>]]></text>
      <feedback format="html">
        <text></text>
      </feedback>
    </answer>
    <answer fraction="0" format="html">
      <text><![CDATA[<p>@d\{(x,y,z) | x=5z+6\text{ and } y=3z-2\}@d</p>]]></text>
      <feedback format="html">
        <text></text>
      </feedback>
    </answer>
    <answer fraction="0" format="html">
      <text><![CDATA[<p>@d\{(x,y,z) | x=-5z+2\text{ and } y=3z-6\}@d</p>]]></text>
      <feedback format="html">
        <text></text>
      </feedback>
    </answer>
    <answer fraction="0" format="html">
      <text><![CDATA[<p>@d\{(x,y,z) | x=5z+2\text{ and } y=3z+6\}@d</p>]]></text>
      <feedback format="html">
        <text></text>
      </feedback>
    </answer>
  </question>

<!-- question: 13  -->
  <question type="multichoice">
    <name>
      <text>Which variables are leading entries</text>
    </name>
    <questiontext format="html">
      <text><![CDATA[<p>@d\begin{array}{rcrcrcrcr} 2x &amp;- &amp;y &amp;+ &amp;z &amp;- &amp;8w &amp;= &amp;2\\ &amp; &amp; &amp; &amp;4z &amp; &amp; &amp;= &amp;0 \end{array}@d</p>]]></text>
    </questiontext>
    <generalfeedback format="html">
      <text></text>
    </generalfeedback>
    <defaultgrade>1.0000000</defaultgrade>
    <penalty>0.3333333</penalty>
    <hidden>0</hidden>
    <single>true</single>
    <shuffleanswers>true</shuffleanswers>
    <answernumbering>abc</answernumbering>
    <correctfeedback format="html">
      <text></text>
    </correctfeedback>
    <partiallycorrectfeedback format="html">
      <text></text>
    </partiallycorrectfeedback>
    <incorrectfeedback format="html">
      <text></text>
    </incorrectfeedback>
    <answer fraction="100" format="html">
      <text><![CDATA[<p>@ix,z@i</p>]]></text>
      <feedback format="html">
        <text></text>
      </feedback>
    </answer>
    <answer fraction="0" format="html">
      <text><![CDATA[<p>@ix,y@i</p>]]></text>
      <feedback format="html">
        <text></text>
      </feedback>
    </answer>
    <answer fraction="0" format="html">
      <text><![CDATA[<p>@iy,w@i</p>]]></text>
      <feedback format="html">
        <text></text>
      </feedback>
    </answer>
    <answer fraction="0" format="html">
      <text><![CDATA[<p>All but @ix@i</p>]]></text>
      <feedback format="html">
        <text></text>
      </feedback>
    </answer>
    <answer fraction="0" format="html">
      <text><![CDATA[<p>Only @ix@i</p>]]></text>
      <feedback format="html">
        <text></text>
      </feedback>
    </answer>
  </question>

<!-- question: 0  -->
  <question type="category">
    <category>
        <text>$course$/Linear Algebra/one_i/Gauss's method</text>

    </category>
  </question>

<!-- question: 7  -->
  <question type="numerical">
    <name>
      <text>One value of solution of linear system</text>
    </name>
    <questiontext format="html">
      <text><![CDATA[<p>What is the value of @iy@i in the solution of this linear system?@d\begin{array}{rcrcrcr} x &amp;- &amp;y &amp;+ &amp;2z &amp;= &amp;1\\ 2x &amp;- &amp;y &amp;+ &amp;z &amp;= &amp;1\\ x &amp; &amp; &amp;+ &amp;3z &amp;= &amp;4 \end{array}@d</p>]]></text>
    </questiontext>
    <generalfeedback format="html">
      <text><![CDATA[<p>Apply Gauss's method</p>]]></text>
    </generalfeedback>
    <defaultgrade>1.0000000</defaultgrade>
    <penalty>0.3333333</penalty>
    <hidden>0</hidden>
    <answer fraction="100" format="moodle_auto_format">
      <text>2</text>
      <feedback format="html">
        <text></text>
      </feedback>
      <tolerance>0</tolerance>
    </answer>
    <unitgradingtype>0</unitgradingtype>
    <unitpenalty>0.1000000</unitpenalty>
    <showunits>3</showunits>
    <unitsleft>0</unitsleft>
  </question>

<!-- question: 5  -->
  <question type="numerical">
    <name>
      <text>One value of solution of linear system</text>
    </name>
    <questiontext format="html">
      <text><![CDATA[<p>What is the value of @iz@i in the solution of this linear system?@d\begin{array}{rcrcrcr} x &amp;- &amp;y &amp;+ &amp;2z &amp;= &amp;1\\ 2x &amp;- &amp;y &amp;+ &amp;z &amp;= &amp;1\\ x &amp; &amp; &amp;+ &amp;3z &amp;= &amp;4 \end{array}@d</p>]]></text>
    </questiontext>
    <generalfeedback format="html">
      <text><![CDATA[<p>Apply Gauss's method</p>]]></text>
    </generalfeedback>
    <defaultgrade>1.0000000</defaultgrade>
    <penalty>0.3333333</penalty>
    <hidden>0</hidden>
    <answer fraction="100" format="moodle_auto_format">
      <text>1</text>
      <feedback format="html">
        <text></text>
      </feedback>
      <tolerance>0</tolerance>
    </answer>
    <unitgradingtype>0</unitgradingtype>
    <unitpenalty>0.1000000</unitpenalty>
    <showunits>3</showunits>
    <unitsleft>0</unitsleft>
  </question>

<!-- question: 0  -->
  <question type="category">
    <category>
        <text>$course$/Linear Algebra/one_i/Describing the solution set</text>

    </category>
  </question>

<!-- question: 10  -->
  <question type="shortanswer">
    <name>
      <text>Find matrix entry from row and column indices</text>
    </name>
    <questiontext format="html">
      <text><![CDATA[<p>What is @ia_{2,3}@i?</p>
<p>@dA=\begin{pmatrix} 2 &amp;1 &amp;4\\ 0 &amp;-1 &amp;5\\ 9 &amp;1/2 &amp;6 \end{pmatrix}@d</p>]]></text>
    </questiontext>
    <generalfeedback format="html">
      <text><![CDATA[<p>The order of the subscripts matters.</p>]]></text>
    </generalfeedback>
    <defaultgrade>1.0000000</defaultgrade>
    <penalty>0.3333333</penalty>
    <hidden>0</hidden>
    <usecase>0</usecase>
    <answer fraction="100" format="moodle_auto_format">
      <text>5</text>
      <feedback format="html">
        <text></text>
      </feedback>
    </answer>
  </question>

<!-- question: 0  -->
  <question type="category">
    <category>
        <text>$course$/Linear Algebra/one_i/Gauss's method</text>

    </category>
  </question>

<!-- question: 4  -->
  <question type="shortanswer">
    <name>
      <text>One variable of solution of simple linear system</text>
    </name>
    <questiontext format="html">
      <text><![CDATA[<p>What is the value of @ix@i in the solution of this linear system?@d\begin{array}{rcrcr} x &amp;+ &amp;y &amp;= &amp;1\\ x &amp;- &amp;y &amp;= &amp;0 \end{array}@d</p>]]></text>
    </questiontext>
    <generalfeedback format="html">
      <text></text>
    </generalfeedback>
    <defaultgrade>1.0000000</defaultgrade>
    <penalty>0.3333333</penalty>
    <hidden>0</hidden>
    <usecase>0</usecase>
    <answer fraction="100" format="moodle_auto_format">
      <text>1/2</text>
      <feedback format="html">
        <text></text>
      </feedback>
    </answer>
    <answer fraction="100" format="moodle_auto_format">
      <text>0.5</text>
      <feedback format="html">
        <text></text>
      </feedback>
    </answer>
    <hint format="html">
      <text><![CDATA[<p>Add the first row to the second.</p>]]></text>
    </hint>
  </question>

<!-- question: 0  -->
  <question type="category">
    <category>
        <text>$course$/Linear Algebra/one_i/Describing the solution set</text>

    </category>
  </question>

<!-- question: 14  -->
  <question type="shortanswer">
    <name>
      <text>What is the second component of this combination of vectors?</text>
    </name>
    <questiontext format="html">
      <text><![CDATA[<p>What is the second component of this combination?</p>
<p>@d3\begin{pmatrix} -5\\ -2\\ 0\end{pmatrix} -4\begin{pmatrix} 1\\ 1\\ 7\end{pmatrix} +2\begin{pmatrix} -2\\ 8\\ 0\end{pmatrix}@d</p>]]></text>
    </questiontext>
    <generalfeedback format="html">
      <text></text>
    </generalfeedback>
    <defaultgrade>1.0000000</defaultgrade>
    <penalty>0.3333333</penalty>
    <hidden>0</hidden>
    <usecase>0</usecase>
    <answer fraction="100" format="moodle_auto_format">
      <text>6</text>
      <feedback format="html">
        <text></text>
      </feedback>
    </answer>
  </question>

<!-- question: 0  -->
  <question type="category">
    <category>
        <text>$course$/Linear Algebra/one_i/Gauss's method</text>

    </category>
  </question>

<!-- question: 8  -->
  <question type="truefalse">
    <name>
      <text>Does the system have a unique solution?</text>
    </name>
    <questiontext format="html">
      <text><![CDATA[<p>This system has a unique solution.@d\begin{array}{rcrcrcr} x &amp;+ &amp;y &amp;+ &amp;z &amp;= &amp;0\\ 2x &amp;+ &amp;y &amp;- &amp;2z &amp;= &amp;2\\ x &amp;+ &amp;2y &amp;+ &amp;5z &amp;= &amp;-1 \end{array}@d</p>]]></text>
    </questiontext>
    <generalfeedback format="html">
      <text></text>
    </generalfeedback>
    <defaultgrade>1.0000000</defaultgrade>
    <penalty>1.0000000</penalty>
    <hidden>0</hidden>
    <answer fraction="0" format="moodle_auto_format">
      <text>true</text>
      <feedback format="html">
        <text><![CDATA[<p>Bring the system to echelon form and notice the impossibility.</p>]]></text>
      </feedback>
    </answer>
    <answer fraction="100" format="moodle_auto_format">
      <text>false</text>
      <feedback format="html">
        <text></text>
      </feedback>
    </answer>
  </question>

<!-- question: 9  -->
  <question type="truefalse">
    <name>
      <text>Does the system have a unique solution? Yes</text>
    </name>
    <questiontext format="html">
      <text><![CDATA[<p>This system has a unique solution.@d\begin{array}{rcrcrcr} x &amp;+ &amp;y &amp;+ &amp;z &amp;= &amp;0\\ 2x &amp;+ &amp;y &amp;- &amp;2z &amp;= &amp;2\\ x &amp;+ &amp;2y &amp;+ &amp;5z &amp;= &amp;-2 \end{array}@d</p>]]></text>
    </questiontext>
    <generalfeedback format="html">
      <text></text>
    </generalfeedback>
    <defaultgrade>1.0000000</defaultgrade>
    <penalty>1.0000000</penalty>
    <hidden>0</hidden>
    <answer fraction="100" format="moodle_auto_format">
      <text>true</text>
      <feedback format="html">
        <text></text>
      </feedback>
    </answer>
    <answer fraction="0" format="moodle_auto_format">
      <text>false</text>
      <feedback format="html">
        <text><![CDATA[<p>Bring the system to echelon form and note that you could apply back-substitution.</p>]]></text>
      </feedback>
    </answer>
  </question>

</quiz>